CHANGELOG.md
LICENSE
MANIFEST.in
README.rst
TODO.rst
peewee.py
pwiz.py
pyproject.toml
runtests.py
setup.py
docs/Makefile
docs/conf.py
docs/crdb.png
docs/index.rst
docs/make.bat
docs/mariadb.png
docs/mysql.png
docs/peewee-logo.png
docs/peewee-white.png
docs/peewee3-logo.png
docs/postgresql.png
docs/requirements.txt
docs/sqlite.png
docs/_static/peewee-white.png
docs/_themes/flask/layout.html
docs/_themes/flask/relations.html
docs/_themes/flask/theme.conf
docs/_themes/flask/static/flasky.css_t
docs/_themes/flask/static/small_flask.css
docs/peewee/api.rst
docs/peewee/changes.rst
docs/peewee/contributing.rst
docs/peewee/crdb.rst
docs/peewee/database.rst
docs/peewee/example.rst
docs/peewee/hacks.rst
docs/peewee/installation.rst
docs/peewee/interactive.rst
docs/peewee/models.rst
docs/peewee/playhouse.rst
docs/peewee/query_builder.rst
docs/peewee/query_examples.rst
docs/peewee/query_operators.rst
docs/peewee/querying.rst
docs/peewee/quickstart.rst
docs/peewee/relationships.rst
docs/peewee/schema-horizontal.png
docs/peewee/schema.jpg
docs/peewee/sqlite_ext.rst
docs/peewee/tweepee.jpg
examples/adjacency_list.py
examples/anomaly_detection.py
examples/diary.py
examples/graph.py
examples/hexastore.py
examples/reddit_ranking.py
examples/sqlite_fts_compression.py
examples/analytics/app.py
examples/analytics/reports.py
examples/analytics/requirements.txt
examples/analytics/run_example.py
examples/analytics/__pycache__/app.cpython-37.pyc
examples/blog/app.py
examples/blog/requirements.txt
examples/blog/static/robots.txt
examples/blog/static/css/blog.min.css
examples/blog/static/css/hilite.css
examples/blog/static/fonts/glyphicons-halflings-regular.eot
examples/blog/static/fonts/glyphicons-halflings-regular.svg
examples/blog/static/fonts/glyphicons-halflings-regular.ttf
examples/blog/static/fonts/glyphicons-halflings-regular.woff
examples/blog/static/js/bootstrap.min.js
examples/blog/static/js/jquery-1.11.0.min.js
examples/blog/templates/base.html
examples/blog/templates/create.html
peewee.egg-info/PKG-INFO
peewee.egg-info/SOURCES.txt
peewee.egg-info/dependency_links.txt
peewee.egg-info/not-zip-safe
peewee.egg-info/top_level.txt
